lacuna/__init__.py
lacuna/__version__.py
lacuna/_version.txt
lacuna/api/__init__.py
lacuna/api/app.py
lacuna/api/routes/__init__.py
lacuna/api/routes/audit.py
lacuna/api/routes/classify.py
lacuna/api/routes/evaluate.py
lacuna/api/routes/health.py
lacuna/api/routes/lineage.py
lacuna/audit/__init__.py
lacuna/audit/backend.py
lacuna/audit/logger.py
lacuna/audit/memory_backend.py
lacuna/auth/__init__.py
lacuna/auth/api_keys.py
lacuna/auth/dependencies.py
lacuna/auth/models.py
lacuna/classifier/__init__.py
lacuna/classifier/base.py
lacuna/classifier/embedding.py
lacuna/classifier/heuristic.py
lacuna/classifier/llm.py
lacuna/classifier/pipeline.py
lacuna/cli/__init__.py
lacuna/cli/admin.py
lacuna/config/__init__.py
lacuna/config/loader.py
lacuna/config/settings.py
lacuna/db/__init__.py
lacuna/db/base.py
lacuna/db/models.py
lacuna/engine/__init__.py
lacuna/engine/governance.py
lacuna/engine/result.py
lacuna/lineage/__init__.py
lacuna/lineage/backend.py
lacuna/lineage/memory_backend.py
lacuna/lineage/tracker.py
lacuna/models/__init__.py
lacuna/models/audit.py
lacuna/models/classification.py
lacuna/models/data_operation.py
lacuna/models/lineage.py
lacuna/models/policy.py
lacuna/policy/__init__.py
lacuna/policy/client.py
lacuna/policy/engine.py
lacuna/web/__init__.py
lacuna/web/routes/__init__.py
lacuna/web/routes/admin.py
lacuna/web/routes/user.py
lacuna-2026.1.51.dist-info/licenses/LICENSE
lacuna-2026.1.51.dist-info/METADATA
lacuna-2026.1.51.dist-info/WHEEL
lacuna-2026.1.51.dist-info/entry_points.txt
lacuna-2026.1.51.dist-info/top_level.txt
lacuna-2026.1.51.dist-info/RECORD
