Metadata-Version: 2.4
Name: lacuna
Version: 2026.1.51
Summary: Privacy-aware query classification and routing for RAG systems - the protected space where your knowledge stays yours
Author: witlox
License: Apache 2.0
Project-URL: Homepage, https://github.com/witlox/lacuna
Project-URL: Documentation, https://witlox.github.io/lacuna
Project-URL: Repository, https://github.com/witlox/lacuna
Project-URL: Issues, https://github.com/witlox/lacuna/issues
Keywords: rag,privacy,llm,query-classification,data-sovereignty,retrieval-augmented-generation,lacuna,pii-detection,privacy-router
Classifier: Development Status :: 3 - Alpha
Classifier: Intended Audience :: Developers
Classifier: Intended Audience :: Science/Research
Classifier: License :: OSI Approved :: Apache Software License
Classifier: Programming Language :: Python :: 3
Classifier: Programming Language :: Python :: 3.9
Classifier: Programming Language :: Python :: 3.10
Classifier: Programming Language :: Python :: 3.11
Classifier: Programming Language :: Python :: 3.12
Classifier: Topic :: Scientific/Engineering :: Artificial Intelligence
Classifier: Topic :: Software Development :: Libraries :: Python Modules
Requires-Python: >=3.9
License-File: LICENSE
Requires-Dist: pyyaml>=6.0.3
Requires-Dist: pydantic>=2.12.5
Requires-Dist: pydantic-settings>=2.11.0
Requires-Dist: python-dotenv>=1.2.1
Requires-Dist: openai>=2.15.0
Requires-Dist: sentence-transformers>=5.1.2
Requires-Dist: torch>=2.8.0
Requires-Dist: qdrant-client>=1.16.1
Requires-Dist: requests>=2.32.5
Requires-Dist: aiohttp>=3.13.3
Requires-Dist: numpy>=2.0.2
Requires-Dist: regex>=2026.1.15
Requires-Dist: tiktoken>=0.12.0
Requires-Dist: prometheus-client>=0.24.1
Requires-Dist: structlog>=25.5.0
Requires-Dist: sqlalchemy>=2.0.45
Requires-Dist: alembic>=1.16.5
Requires-Dist: psycopg2-binary>=2.9.11
Requires-Dist: networkx>=3.2.1
Requires-Dist: fastapi>=0.128.0
Requires-Dist: uvicorn[standard]>=0.39.0
Requires-Dist: python-multipart>=0.0.20
Requires-Dist: jinja2>=3.1.5
Requires-Dist: redis>=7.0.1
Requires-Dist: tenacity>=9.1.2
Requires-Dist: click>=8.1.8
Provides-Extra: dev
Requires-Dist: pytest>=8.4.2; extra == "dev"
Requires-Dist: pytest-cov>=7.0.0; extra == "dev"
Requires-Dist: pytest-asyncio>=1.2.0; extra == "dev"
Requires-Dist: pytest-mock>=3.15.1; extra == "dev"
Requires-Dist: black>=25.11.0; extra == "dev"
Requires-Dist: ruff>=0.14.13; extra == "dev"
Requires-Dist: mypy>=1.19.1; extra == "dev"
Requires-Dist: pre-commit>=4.3.0; extra == "dev"
Requires-Dist: types-PyYAML>=6.0.0; extra == "dev"
Requires-Dist: types-requests>=2.31.0; extra == "dev"
Provides-Extra: docs
Requires-Dist: mkdocs>=1.6.1; extra == "docs"
Requires-Dist: mkdocs-material>=9.5.54; extra == "docs"
Requires-Dist: pymdown-extensions>=10.15; extra == "docs"
Provides-Extra: llamaindex
Requires-Dist: llama-index-core>=0.14.12; extra == "llamaindex"
Provides-Extra: langchain
Requires-Dist: langchain>=0.3.27; extra == "langchain"
Requires-Dist: langchain-community>=0.3.31; extra == "langchain"
Provides-Extra: chromadb
Requires-Dist: chromadb>=1.4.1; extra == "chromadb"
Provides-Extra: milvus
Requires-Dist: pymilvus>=2.6.6; extra == "milvus"
Provides-Extra: plugins-individual
Requires-Dist: presidio-analyzer>=2.2.360; extra == "plugins-individual"
Requires-Dist: presidio-anonymizer>=2.2.360; extra == "plugins-individual"
Requires-Dist: spacy>=3.8.11; extra == "plugins-individual"
Requires-Dist: setfit>=1.1.3; extra == "plugins-individual"
Provides-Extra: plugins-enterprise
Requires-Dist: presidio-analyzer>=2.2.360; extra == "plugins-enterprise"
Requires-Dist: presidio-anonymizer>=2.2.360; extra == "plugins-enterprise"
Requires-Dist: spacy>=3.8.11; extra == "plugins-enterprise"
Requires-Dist: setfit>=1.1.3; extra == "plugins-enterprise"
Requires-Dist: opa-python-client>=2.0.3; extra == "plugins-enterprise"
Provides-Extra: plugins-healthcare
Requires-Dist: presidio-analyzer>=2.2.360; extra == "plugins-healthcare"
Requires-Dist: presidio-anonymizer>=2.2.360; extra == "plugins-healthcare"
Requires-Dist: spacy>=3.8.11; extra == "plugins-healthcare"
Requires-Dist: scispacy>=0.6.2; extra == "plugins-healthcare"
Provides-Extra: plugins-finance
Requires-Dist: presidio-analyzer>=2.2.360; extra == "plugins-finance"
Requires-Dist: presidio-anonymizer>=2.2.360; extra == "plugins-finance"
Provides-Extra: cloud-azure
Requires-Dist: azure-ai-textanalytics>=5.3.0; extra == "cloud-azure"
Provides-Extra: cloud-gcp
Requires-Dist: google-cloud-dlp>=3.34.0; extra == "cloud-gcp"
Provides-Extra: plugins-all
Requires-Dist: lacuna[plugins-enterprise,plugins-finance,plugins-healthcare,plugins-individual]; extra == "plugins-all"
Provides-Extra: all
Requires-Dist: lacuna[chromadb,dev,langchain,llamaindex,milvus,plugins-all]; extra == "all"
Dynamic: license-file
